ood_detectors/__about__.py
ood_detectors/__init__.py
ood_detectors/ema.py
ood_detectors/eval_utils.py
ood_detectors/knn.py
ood_detectors/likelihood.py
ood_detectors/list_dataset.py
ood_detectors/losses.py
ood_detectors/models.py
ood_detectors/nlp.py
ood_detectors/ood_utils.py
ood_detectors/ops_utils.py
ood_detectors/plot_utils.py
ood_detectors/residual.py
ood_detectors/sde.py
ood_detectors/train.py
ood_detectors/vision.py
ood_detectors-0.0.58.dist-info/METADATA
ood_detectors-0.0.58.dist-info/WHEEL
ood_detectors-0.0.58.dist-info/licenses/LICENSE
ood_detectors-0.0.58.dist-info/RECORD
