Metadata-Version: 2.4
Name: ood_detectors
Version: 0.0.58
Project-URL: Documentation, https://github.com/Arty-Facts/ood_detectors#readme
Project-URL: Issues, https://github.com/Arty-Facts/ood_detectors/issues
Project-URL: Source, https://github.com/Arty-Facts/ood_detectors
Author-email: Arturas Aleksandraus <arturas@aleksandraus.se>, Yifan Ding <yifan.ding@liu.se>
License-Expression: Apache-2.0
License-File: LICENSE
Classifier: Development Status :: 3 - Alpha
Classifier: Programming Language :: Python
Classifier: Programming Language :: Python :: 3.8
Classifier: Programming Language :: Python :: 3.9
Classifier: Programming Language :: Python :: 3.10
Classifier: Programming Language :: Python :: 3.11
Classifier: Programming Language :: Python :: 3.12
Classifier: Programming Language :: Python :: Implementation :: CPython
Classifier: Programming Language :: Python :: Implementation :: PyPy
Requires-Python: >=3.8
Requires-Dist: docker
Requires-Dist: einops
Requires-Dist: faiss-cpu
Requires-Dist: gdown
Requires-Dist: jupyter
Requires-Dist: matplotlib
Requires-Dist: notebook
Requires-Dist: numpy
Requires-Dist: nvidia-ml-py3
Requires-Dist: openmim
Requires-Dist: pynvml
Requires-Dist: scikit-learn
Requires-Dist: seaborn
Requires-Dist: timm
Requires-Dist: torch
Requires-Dist: torchdiffeq
Requires-Dist: tqdm
